Workbook

Sheet ①入力データ
A1: 在庫・DOS予測モデル v3 ― 入力データ
A2: 黄色=手入力 白色=自動計算/既知データ
A4: 【基準値】
A5: Luna 2月末 実績在庫金額（円）
A6: ToC換算率（消費税） | B6: 1.1
A7: ToB換算率 | B7: 0.72
A8: 店舗進货 当月着荷率 | B8: 0.3
A10: 月 | B10: 1月 | C10: 2月 | D10: 3月 | E10: 4月 | F10: 5月 | G10: 6月 | H10: 7月 | I10: 8月 | J10: 9月 | K10: 10月 | L10: 11月 | M10: 12月
A12: 【販売予算（Sell Out）】
A13: 店舗（既存） | B13: 1699940255 | C13: 1313219737 | D13: 1470783378 | E13: 1801379308 | F13: 1874294789 | G13: 1911750692 | H13: 1925967529 | I13: 1893433375 | J13: 1711900823 | K13: 1663896416 | L13: 1523414395 | M13: 1349930172
A14: 店舗（新規Open）
A15: ROBO | B15: 73558644 | C15: 56824740 | D15: 63642725 | E15: 77948044 | F15: 81103193 | G15: 82723959 | H15: 83339140 | I15: 81931345 | J15: 74076193 | K15: 71998979 | L15: 65920138 | M15: 58413248
A16: B2B
A17: 販売合計（ToC） | B17: =B13+B14+B15 | C17: =C13+C14+C15 | D17: =D13+D14+D15 | E17: =E13+E14+E15 | F17: =F13+F14+F15 | G17: =G13+G14+G15 | H17: =H13+H14+H15 | I17: =I13+I14+I15 | ... M17: =M13+M14+M15
A18: 販売合計（ToB = B2B） | B18: =B16 | C18: =C16 | D18: =D16 | E18: =E16 | F18: =F16 | G18: =G16 | H18: =H16 | I18: =I16 | ... M18: =M16
A19: 販売合計（全体） | B19: =B17+B18 | C19: =C17+C18 | D19: =D17+D18 | E19: =E17+E18 | F19: =F17+F18 | G19: =G17+G18 | H19: =H17+H18 | I19: =I17+I18 | ... M19: =M17+M18
A21: 【進货計画・EC移管】
A22: 店舗 進货計画 | B22: 2317652861 | C22: 850096243 | D22: 1315131747 | E22: 1472696605 | F22: 1460578854 | G22: 2024355831 | H22: 1835776567 | I22: 1529507202 | J22: 1502459212 | K22: 1230694625 | L22: 806516283 | M22: 773997069
A23: EC移管金額（Luna着荷） | B23: 147846918
A24: 入庫合計 | B24: =B22*$B$8+B23 | C24: =C22*$B$8+B22*(1-$B$8)+C23 | D24: =D22*$B$8+C22*(1-$B$8)+D23 | E24: =E22*$B$8+D22*(1-$B$8)+E23 | F24: =F22*$B$8+E22*(1-$B$8)+F23 | G24: =G22*$B$8+F22*(1-$B$8)+G23 | H24: =H22*$B$8+G22*(1-$B$8)+H23 | I24: =I22*$B$8+H22*(1-$B$8)+I23 | J24: =J22*$B$8+I22*(1-$B$8)+J23 | ... M24: =M22*$B$8+L22*(1-$B$8)+M23
A26: 【新規開店計画】
A27: 新規開店数（店）
A28: 累計店舗数（既存+新規）

Sheet ②予測計算
A1: 在庫・DOS 月次予測計算
B3: 1月 | C3: 2月 | D3: 3月 | E3: 4月 | F3: 5月 | G3: 6月 | H3: 7月 | I3: 8月 | J3: 9月 | K3: 10月 | L3: 11月 | M3: 12月
A5: 【在庫ロールフォワード】
A6: 月初在庫 | B6: 0 | C6: =B9 | D6: =C9 | E6: =D9 | F6: =E9 | G6: =F9 | H6: =G9 | I6: =H9 | J6: =I9 | ... M6: =L9
A7: 入庫合計 | B7: ='①入力データ'!B24 | C7: ='①入力データ'!C24 | D7: ='①入力データ'!D24 | E7: ='①入力データ'!E24 | F7: ='①入力データ'!F24 | G7: ='①入力データ'!G24 | H7: ='①入力データ'!H24 | I7: ='①入力データ'!I24 | ... M7: ='①入力データ'!M24
A8: Sell Out消費（原価換算） | B8: ='①入力データ'!B17/$B$6+'①入力データ'!B18/$B$7 | C8: ='①入力データ'!C17/$B$6+'①入力データ'!C18/$B$7 | D8: ='①入力データ'!D17/$B$6+'①入力データ'!D18/$B$7 | E8: ='①入力データ'!E17/$B$6+'①入力データ'!E18/$B$7 | F8: ='①入力データ'!F17/$B$6+'①入力データ'!F18/$B$7 | G8: ='①入力データ'!G17/$B$6+'①入力データ'!G18/$B$7 | H8: ='①入力データ'!H17/$B$6+'①入力データ'!H18/$B$7 | I8: ='①入力データ'!I17/$B$6+'①入力データ'!I18/$B$7 | ... M8: ='①入力データ'!M17/$B$6+'①入力データ'!M18/$B$7
A9: 月末在庫 | C9: ='①入力データ'!B5 | D9: =D6+D7-D8 | E9: =E6+E7-E8 | F9: =F6+F7-F8 | G9: =G6+G7-G8 | H9: =H6+H7-H8 | I9: =I6+I7-I8 | J9: =J6+J7-J8 | K9: =K6+K7-K8 | ... M9: =M6+M7-M8
A11: 【DOS計算（月数単位）】
A12: 月次消費量（原価換算） | B12: =B8 | C12: =C8 | D12: =D8 | E12: =E8 | F12: =F8 | G12: =G8 | H12: =H8 | I12: =I8 | ... M12: =M8
A13: 2027年1月消費量（参考） | B13: =B12
A14: DOS（月数） | B14: =IF(B9<C12,B9/C12,IF(B9<C12+D12,1+(B9-C12)/D12,2+(B9-C12-D12)/E12)) | C14: =IF(C9<D12,C9/D12,IF(C9<D12+E12,1+(C9-D12)/E12,2+(C9-D12-E12)/F12)) | D14: =IF(D9<E12,D9/E12,IF(D9<E12+F12,1+(D9-E12)/F12,2+(D9-E12-F12)/G12)) | E14: =IF(E9<F12,E9/F12,IF(E9<F12+G12,1+(E9-F12)/G12,2+(E9-F12-G12)/H12)) | F14: =IF(F9<G12,F9/G12,IF(F9<G12+H12,1+(F9-G12)/H12,2+(F9-G12-H12)/I12)) | G14: =IF(G9<H12,G9/H12,IF(G9<H12+I12,1+(G9-H12)/I12,2+(G9-H12-I12)/J12)) | H14: =IF(H9<I12,H9/I12,IF(H9<I12+J12,1+(H9-I12)/J12,2+(H9-I12-J12)/K12)) | I14: =IF(I9<J12,I9/J12,IF(I9<J12+K12,1+(I9-J12)/K12,2+(I9-J12-K12)/L12)) | J14: =IF(J9<K12,J9/K12,IF(J9<K12+L12,1+(J9-K12)/L12,2+(J9-K12-L12)/M12)) | K14: =IF((L12+M12)/2>0,K9/(L12+M12)/2,0) | L14: =IF(M12>0,L9/M12,0) | M14: =IF(B13>0,M9/B13,0)

Sheet ③サマリ
A1: サマリダッシュボード ― 月次在庫・DOS推移
B3: 1月 | C3: 2月 | D3: 3月 | E3: 4月 | F3: 5月 | G3: 6月 | H3: 7月 | I3: 8月 | J3: 9月 | K3: 10月 | L3: 11月 | M3: 12月
A5: Sell Out 販売合計 | B5: ='①入力データ'!B19 | C5: ='①入力データ'!C19 | D5: ='①入力データ'!D19 | E5: ='①入力データ'!E19 | F5: ='①入力データ'!F19 | G5: ='①入力データ'!G19 | H5: ='①入力データ'!H19 | I5: ='①入力データ'!I19 | ... M5: ='①入力データ'!M19
A6: うちToC | B6: ='①入力データ'!B17 | C6: ='①入力データ'!C17 | D6: ='①入力データ'!D17 | E6: ='①入力データ'!E17 | F6: ='①入力データ'!F17 | G6: ='①入力データ'!G17 | H6: ='①入力データ'!H17 | I6: ='①入力データ'!I17 | ... M6: ='①入力データ'!M17
A7: うちToB | B7: ='①入力データ'!B18 | C7: ='①入力データ'!C18 | D7: ='①入力データ'!D18 | E7: ='①入力データ'!E18 | F7: ='①入力データ'!F18 | G7: ='①入力データ'!G18 | H7: ='①入力データ'!H18 | I7: ='①入力データ'!I18 | ... M7: ='①入力データ'!M18
A8: 入庫合計 | B8: ='①入力データ'!B24 | C8: ='①入力データ'!C24 | D8: ='①入力データ'!D24 | E8: ='①入力データ'!E24 | F8: ='①入力データ'!F24 | G8: ='①入力データ'!G24 | H8: ='①入力データ'!H24 | I8: ='①入力データ'!I24 | ... M8: ='①入力データ'!M24
A9: 店舗進货 | B9: ='①入力データ'!B22 | C9: ='①入力データ'!C22 | D9: ='①入力データ'!D22 | E9: ='①入力データ'!E22 | F9: ='①入力データ'!F22 | G9: ='①入力データ'!G22 | H9: ='①入力データ'!H22 | I9: ='①入力データ'!I22 | ... M9: ='①入力データ'!M22
A10: EC移管 | B10: ='①入力データ'!B23 | C10: ='①入力データ'!C23 | D10: ='①入力データ'!D23 | E10: ='①入力データ'!E23 | F10: ='①入力データ'!F23 | G10: ='①入力データ'!G23 | H10: ='①入力データ'!H23 | I10: ='①入力データ'!I23 | ... M10: ='①入力データ'!M23
A11: 消費量（原価換算） | B11: ='②予測計算'!B8 | C11: ='②予測計算'!C8 | D11: ='②予測計算'!D8 | E11: ='②予測計算'!E8 | F11: ='②予測計算'!F8 | G11: ='②予測計算'!G8 | H11: ='②予測計算'!H8 | I11: ='②予測計算'!I8 | ... M11: ='②予測計算'!M8
A12: 月末在庫金額 | B12: ='②予測計算'!B9 | C12: ='②予測計算'!C9 | D12: ='②予測計算'!D9 | E12: ='②予測計算'!E9 | F12: ='②予測計算'!F9 | G12: ='②予測計算'!G9 | H12: ='②予測計算'!H9 | I12: ='②予測計算'!I9 | ... M12: ='②予測計算'!M9
A13: DOS（月数） | B13: ='②予測計算'!B14 | C13: ='②予測計算'!C14 | D13: ='②予測計算'!D14 | E13: ='②予測計算'!E14 | F13: ='②予測計算'!F14 | G13: ='②予測計算'!G14 | H13: ='②予測計算'!H14 | I13: ='②予測計算'!I14 | ... M13: ='②予測計算'!M14
